pstk/__init__.py
pstk/main_cli.py
pstk-0.0.2.dist-info/LICENSE
pstk-0.0.2.dist-info/METADATA
pstk-0.0.2.dist-info/WHEEL
pstk-0.0.2.dist-info/entry_points.txt
pstk-0.0.2.dist-info/RECORD
