Metadata-Version: 2.1
Name: pstk
Version: 0.0.2
Summary: A toolkit for developing Postgres schemas & extensions.
Author: albaike
Requires-Python: >=3.8,<4.0
Classifier: Programming Language :: Python :: 3
Classifier: Programming Language :: Python :: 3.8
Classifier: Programming Language :: Python :: 3.9
Classifier: Programming Language :: Python :: 3.10
Classifier: Programming Language :: Python :: 3.11
Classifier: Programming Language :: Python :: 3.12
Requires-Dist: psycopg2 (>=2.9.9,<3.0.0)
Requires-Dist: python-dotenv (>=1.0.1,<2.0.0)
